{
  "version": "https://jsonfeed.org/version/1",
  "title": "Instagram feed",
  "home_page_url": "https://katydecorah.com/",
  "description": "Public Instagram accounts I want to watch",
  "items": [
    {
      "id": "2512815542967860383",
      "content_html": "<p>New specials have arrived!\n\n#dinnerspecials #specials #happyfriday #capitalregionfoodies #ballstonspa #livebspa #eatnextdoor</p><p><img src=\"https://scontent-lga3-2.cdninstagram.com/v/t51.2885-15/e35/151242705_248183446839486_7889442466555577442_n.jpg?_nc_ht=scontent-lga3-2.cdninstagram.com&_nc_cat=106&_nc_ohc=cwSDHLDyrFkAX8cK4V9&tp=1&oh=c4108e77da48c7991530bdb9d8895710&oe=605A2D6C\" alt=\"\" /></p>",
      "url": "https://instagram.com/p/CLfUGxArfyf",
      "title": "New specials have arrived",
      "image": "https://scontent-lga3-2.cdninstagram.com/v/t51.2885-15/e35/151242705_248183446839486_7889442466555577442_n.jpg?_nc_ht=scontent-lga3-2.cdninstagram.com&_nc_cat=106&_nc_ohc=cwSDHLDyrFkAX8cK4V9&tp=1&oh=c4108e77da48c7991530bdb9d8895710&oe=605A2D6C",
      "date_modified": "2021-02-19T21:42:59.000Z",
      "author": {
        "name": "nextdoorkitchenandbar"
      }
    },
    {
      "id": "2512077589940928467",
      "content_html": "<p>Braised Beef Short Rib\n\nmashed potatoes, roasted carrots, pearl onions, braising jus, persillade\n\n#braisedshortrib #shortrib #beefshortrib #instaeat #51ate #glutenfree #ballstonspa #eatnextdoor</p><p><img src=\"https://scontent-lga3-2.cdninstagram.com/v/t51.2885-15/e35/s1080x1080/150945093_874876723356119_8355839861483931436_n.jpg?_nc_ht=scontent-lga3-2.cdninstagram.com&_nc_cat=111&_nc_ohc=stUP99uw89gAX-dZ7p6&tp=1&oh=e11080779e85639faa35ea74f40eaed7&oe=605AE225\" alt=\"\" /></p>",
      "url": "https://instagram.com/p/CLcsUIspf_T",
      "title": "Braised Beef Short Rib",
      "image": "https://scontent-lga3-2.cdninstagram.com/v/t51.2885-15/e35/s1080x1080/150945093_874876723356119_8355839861483931436_n.jpg?_nc_ht=scontent-lga3-2.cdninstagram.com&_nc_cat=111&_nc_ohc=stUP99uw89gAX-dZ7p6&tp=1&oh=e11080779e85639faa35ea74f40eaed7&oe=605AE225",
      "date_modified": "2021-02-18T21:16:46.000Z",
      "author": {
        "name": "nextdoorkitchenandbar"
      }
    },
    {
      "id": "2511346889654705219",
      "content_html": "<p>Dinner at home is so much better with Next Door takeout! Plus our takeout containers are compostable.\n\nOrder online: www.nextdoorkitchenandbar.com\n\n#takeout #518takeout #saratogatakeout #capitalregiontakeout #ballstonspa #eatnextdoor</p><p><img src=\"https://scontent-lga3-2.cdninstagram.com/v/t51.2885-15/e35/s1080x1080/151268761_163441155422374_3082632734941369173_n.jpg?_nc_ht=scontent-lga3-2.cdninstagram.com&_nc_cat=110&_nc_ohc=gkMJO3VA8ZUAX-ZWIVV&tp=1&oh=1ad42f471eb74768f256b9322cd1c14c&oe=605B110F\" alt=\"\" /></p>",
      "url": "https://instagram.com/p/CLaGLDBppxD",
      "title": "Dinner at home is so much better with Next Door takeout",
      "image": "https://scontent-lga3-2.cdninstagram.com/v/t51.2885-15/e35/s1080x1080/151268761_163441155422374_3082632734941369173_n.jpg?_nc_ht=scontent-lga3-2.cdninstagram.com&_nc_cat=110&_nc_ohc=gkMJO3VA8ZUAX-ZWIVV&tp=1&oh=1ad42f471eb74768f256b9322cd1c14c&oe=605B110F",
      "date_modified": "2021-02-17T21:05:00.000Z",
      "author": {
        "name": "nextdoorkitchenandbar"
      }
    },
    {
      "id": "2511257152243783797",
      "content_html": "<p>So - we will be closed for service this week. We have too many people quarantined for potential exposure to run the restaurants smoothly. As a result, we are taking the week off. Here are some pictures of our staff that we are trying to keep safe and healthy. Hope to see you next week!  #effcovid @henrysttaproom</p><p><img src=\"https://scontent-lga3-2.cdninstagram.com/v/t51.2885-15/e35/s1080x1080/150523403_724310135115837_6914540726036647853_n.jpg?_nc_ht=scontent-lga3-2.cdninstagram.com&_nc_cat=109&_nc_ohc=GoNBnKseOHEAX-TotLW&tp=1&oh=dc62e285f6e503e37bc78bc904a12de2&oe=605ACA8C\" alt=\"\" /></p>",
      "url": "https://instagram.com/p/CLZxxMjJlh1",
      "title": "So - we will be closed for service this week",
      "image": "https://scontent-lga3-2.cdninstagram.com/v/t51.2885-15/e35/s1080x1080/150523403_724310135115837_6914540726036647853_n.jpg?_nc_ht=scontent-lga3-2.cdninstagram.com&_nc_cat=109&_nc_ohc=GoNBnKseOHEAX-TotLW&tp=1&oh=dc62e285f6e503e37bc78bc904a12de2&oe=605ACA8C",
      "date_modified": "2021-02-17T18:06:42.000Z",
      "author": {
        "name": "flatbread.social"
      }
    },
    {
      "id": "2510589545706514125",
      "content_html": "<p>Mixed Greens\n\napple, celery, walnut, blue cheese, dried cranberry, sherry vinaigrette\n\n#mixedgreens #salad #yum #foodgram #upstateeats #upstatefoodies #upstate #eatnextdoor</p><p><img src=\"https://scontent-lga3-2.cdninstagram.com/v/t51.2885-15/e35/s1080x1080/151060755_463052641546152_6350222688535008896_n.jpg?_nc_ht=scontent-lga3-2.cdninstagram.com&_nc_cat=100&_nc_ohc=weW8E0MkBHsAX_Et6ER&tp=1&oh=023e200ca864e2b4258213dc0fdc79b4&oe=605AAC32\" alt=\"\" /></p>",
      "url": "https://instagram.com/p/CLXZ-PgpWbN",
      "title": "Mixed Greens",
      "image": "https://scontent-lga3-2.cdninstagram.com/v/t51.2885-15/e35/s1080x1080/151060755_463052641546152_6350222688535008896_n.jpg?_nc_ht=scontent-lga3-2.cdninstagram.com&_nc_cat=100&_nc_ohc=weW8E0MkBHsAX_Et6ER&tp=1&oh=023e200ca864e2b4258213dc0fdc79b4&oe=605AAC32",
      "date_modified": "2021-02-16T20:00:17.000Z",
      "author": {
        "name": "nextdoorkitchenandbar"
      }
    },
    {
      "id": "2509890616820135641",
      "content_html": "<p>French Onion Soup\n\nshort rib, gruyere crostini, chives\n\n#frenchonionsoup #soup #comfortfood #culinary #518food #saratogafood #ballstonspa #eatnextdoor</p><p><img src=\"https://scontent-lga3-2.cdninstagram.com/v/t51.2885-15/e35/s1080x1080/149785625_356177358953868_4798984223005664420_n.jpg?_nc_ht=scontent-lga3-2.cdninstagram.com&_nc_cat=100&_nc_ohc=Ak3FPV4z54oAX_SUGhX&tp=1&oh=7d86be9bc13c3bb617bf4535c38d8b0c&oe=6059D3CD\" alt=\"\" /></p>",
      "url": "https://instagram.com/p/CLU7DfQpnbZ",
      "title": "French Onion Soup",
      "image": "https://scontent-lga3-2.cdninstagram.com/v/t51.2885-15/e35/s1080x1080/149785625_356177358953868_4798984223005664420_n.jpg?_nc_ht=scontent-lga3-2.cdninstagram.com&_nc_cat=100&_nc_ohc=Ak3FPV4z54oAX_SUGhX&tp=1&oh=7d86be9bc13c3bb617bf4535c38d8b0c&oe=6059D3CD",
      "date_modified": "2021-02-15T20:51:39.000Z",
      "author": {
        "name": "nextdoorkitchenandbar"
      }
    },
    {
      "id": "2509049519139028037",
      "content_html": "<p>We’re sorry to announce that we will be closed for today. We’ve been informed that an employee tested positive for COVID. We will be closed today for a deep clean and are following all necessary guidelines. Stay safe!</p><p><img src=\"https://scontent-lga3-2.cdninstagram.com/v/t51.2885-15/e35/s1080x1080/149408084_1180405395730863_5697916641246488925_n.jpg?_nc_ht=scontent-lga3-2.cdninstagram.com&_nc_cat=103&_nc_ohc=rEvwnuCUDEoAX9DNCVx&tp=1&oh=52a998e0b6250d46ed5dc51fa13f86e5&oe=605C1268\" alt=\"\" /></p>",
      "url": "https://instagram.com/p/CLR7z6AJXxF",
      "title": "We’re sorry to announce that we will be closed for today",
      "image": "https://scontent-lga3-2.cdninstagram.com/v/t51.2885-15/e35/s1080x1080/149408084_1180405395730863_5697916641246488925_n.jpg?_nc_ht=scontent-lga3-2.cdninstagram.com&_nc_cat=103&_nc_ohc=rEvwnuCUDEoAX9DNCVx&tp=1&oh=52a998e0b6250d46ed5dc51fa13f86e5&oe=605C1268",
      "date_modified": "2021-02-14T17:00:32.000Z",
      "author": {
        "name": "flatbread.social"
      }
    },
    {
      "id": "2508989223679063135",
      "content_html": "<p>Happy Valentine’s Day! We look forward to seeing all of you lovebirds tonight for our very special Valentine’s Day dinner.\n\n#valentinesday #valentinesday2021 #valentinesdaydinner #love #loveisintheair #eatnextdoor</p><p><img src=\"https://scontent-lga3-2.cdninstagram.com/v/t51.2885-15/e35/149764695_169929768262656_4528047029278735716_n.jpg?_nc_ht=scontent-lga3-2.cdninstagram.com&_nc_cat=100&_nc_ohc=F8zo4DZQ_ecAX83A6uM&tp=1&oh=aec56c7c583276401b78aa1b62cd698e&oe=605AD612\" alt=\"\" /></p>",
      "url": "https://instagram.com/p/CLRuGferHRf",
      "title": "Happy Valentine’s Day",
      "image": "https://scontent-lga3-2.cdninstagram.com/v/t51.2885-15/e35/149764695_169929768262656_4528047029278735716_n.jpg?_nc_ht=scontent-lga3-2.cdninstagram.com&_nc_cat=100&_nc_ohc=F8zo4DZQ_ecAX83A6uM&tp=1&oh=aec56c7c583276401b78aa1b62cd698e&oe=605AD612",
      "date_modified": "2021-02-14T15:00:46.000Z",
      "author": {
        "name": "nextdoorkitchenandbar"
      }
    },
    {
      "id": "2508264367308315098",
      "content_html": "<p>Start your Valentine’s Day celebrations early tonight with our Winter Cocktails!\n\nReservations: 518-309-3249\n\nTakeout: www.nextdoorkitchenandbar.com \n\n#valentinesday #valentinesday2021 #saratogadrinks #518drinks #ballstonspa #livebspa #eatnextdoor</p><p><img src=\"https://scontent-lga3-2.cdninstagram.com/v/t51.2885-15/e35/s1080x1080/148962595_116157870372267_5682296705479594455_n.jpg?_nc_ht=scontent-lga3-2.cdninstagram.com&_nc_cat=103&_nc_ohc=TBFzEiukciEAX-qVW7K&tp=1&oh=447318c8770ecbc2dac2d04074df394c&oe=605AFD96\" alt=\"\" /></p>",
      "url": "https://instagram.com/p/CLPJScYLpna",
      "title": "Start your Valentine’s Day celebrations early tonight with our Winter Cocktails",
      "image": "https://scontent-lga3-2.cdninstagram.com/v/t51.2885-15/e35/s1080x1080/148962595_116157870372267_5682296705479594455_n.jpg?_nc_ht=scontent-lga3-2.cdninstagram.com&_nc_cat=103&_nc_ohc=TBFzEiukciEAX-qVW7K&tp=1&oh=447318c8770ecbc2dac2d04074df394c&oe=605AFD96",
      "date_modified": "2021-02-13T15:00:38.000Z",
      "author": {
        "name": "nextdoorkitchenandbar"
      }
    },
    {
      "id": "2507741920976193970",
      "content_html": "<p>A preview of our current specials…\n\n#dinnerspecials #specials #capitalregioneats #downtownballstonspa #upstatenewyork #eatnextdoor</p><p><img src=\"https://scontent-lga3-2.cdninstagram.com/v/t51.2885-15/e35/148730007_1151403421945939_8510323591516387090_n.jpg?_nc_ht=scontent-lga3-2.cdninstagram.com&_nc_cat=107&_nc_ohc=_Ejaqgn7gqUAX_A_Bxn&tp=1&oh=9d23db4d9b27fe245f139ca6c18c5a2c&oe=605C85DB\" alt=\"\" /></p>",
      "url": "https://instagram.com/p/CLNSf2UJEmy",
      "title": "A preview of our current specials…",
      "image": "https://scontent-lga3-2.cdninstagram.com/v/t51.2885-15/e35/148730007_1151403421945939_8510323591516387090_n.jpg?_nc_ht=scontent-lga3-2.cdninstagram.com&_nc_cat=107&_nc_ohc=_Ejaqgn7gqUAX_A_Bxn&tp=1&oh=9d23db4d9b27fe245f139ca6c18c5a2c&oe=605C85DB",
      "date_modified": "2021-02-12T21:42:34.000Z",
      "author": {
        "name": "nextdoorkitchenandbar"
      }
    },
    {
      "id": "2506891108918030743",
      "content_html": "<p>We still have a few reservations available for our Valentine’s Day five course dinner! Call 518-309-3249\n\n#valentinesday #valentinesday2021 #edible518 #saratoga #ballstonspa #upstateny #eatnextdoor</p><p><img src=\"https://scontent-lga3-2.cdninstagram.com/v/t51.2885-15/e35/s1080x1080/148847267_1149248558841147_5421537881276720494_n.jpg?_nc_ht=scontent-lga3-2.cdninstagram.com&_nc_cat=103&_nc_ohc=YgO9PA5XA1UAX_Qp-RG&tp=1&oh=21b758078e0bfddedc622c8eed9961df&oe=60591776\" alt=\"\" /></p>",
      "url": "https://instagram.com/p/CLKRC51pPGX",
      "title": "We still have a few reservations available for our Valentine’s Day five course dinner",
      "image": "https://scontent-lga3-2.cdninstagram.com/v/t51.2885-15/e35/s1080x1080/148847267_1149248558841147_5421537881276720494_n.jpg?_nc_ht=scontent-lga3-2.cdninstagram.com&_nc_cat=103&_nc_ohc=YgO9PA5XA1UAX_Qp-RG&tp=1&oh=21b758078e0bfddedc622c8eed9961df&oe=60591776",
      "date_modified": "2021-02-11T17:32:09.000Z",
      "author": {
        "name": "nextdoorkitchenandbar"
      }
    },
    {
      "id": "2506366560334505181",
      "content_html": "<p>This Week’s Pizza Special:  Brie Cheese, Balsamic, Pears, Arugula, Pistachio. That’s a fancy and delicious pie right there. #spreadthebread #woodfiredpizza</p><p><img src=\"https://scontent-lga3-2.cdninstagram.com/v/t51.2885-15/e35/p1080x1080/148240010_422078458895156_6934245857312956844_n.jpg?_nc_ht=scontent-lga3-2.cdninstagram.com&_nc_cat=108&_nc_ohc=5IFm1KN5AcsAX9TLL8s&tp=1&oh=20a831e79399872df553d6fb58ba432d&oe=60594EA9\" alt=\"\" /></p>",
      "url": "https://instagram.com/p/CLIZxt5p-Td",
      "title": "This Week’s Pizza Special:  Brie Cheese, Balsamic, Pears, Arugula, Pistachio",
      "image": "https://scontent-lga3-2.cdninstagram.com/v/t51.2885-15/e35/p1080x1080/148240010_422078458895156_6934245857312956844_n.jpg?_nc_ht=scontent-lga3-2.cdninstagram.com&_nc_cat=108&_nc_ohc=5IFm1KN5AcsAX9TLL8s&tp=1&oh=20a831e79399872df553d6fb58ba432d&oe=60594EA9",
      "date_modified": "2021-02-11T00:09:58.000Z",
      "author": {
        "name": "flatbread.social"
      }
    },
    {
      "id": "2506261809127130597",
      "content_html": "<p>Today is the LAST DAY to pre-order your Valentine’s Day Takeout Package! Call 518-309-3249\n\n#valentinesday #valentinesday2021 #518takeout #saratogatakeout #livebspa #eatnextdoor</p><p><img src=\"https://scontent-lga3-2.cdninstagram.com/v/t51.2885-15/e35/p1080x1080/148333713_476723093337387_77220793389106995_n.jpg?_nc_ht=scontent-lga3-2.cdninstagram.com&_nc_cat=103&_nc_ohc=E1tDzV4qYjsAX_ZPYSo&tp=1&oh=ebe89df3cf5845430d343b1dd270d9e7&oe=605BE302\" alt=\"\" /></p>",
      "url": "https://instagram.com/p/CLIB9YvJoXl",
      "title": "Today is the LAST DAY to pre-order your Valentine’s Day Takeout Package",
      "image": "https://scontent-lga3-2.cdninstagram.com/v/t51.2885-15/e35/p1080x1080/148333713_476723093337387_77220793389106995_n.jpg?_nc_ht=scontent-lga3-2.cdninstagram.com&_nc_cat=103&_nc_ohc=E1tDzV4qYjsAX_ZPYSo&tp=1&oh=ebe89df3cf5845430d343b1dd270d9e7&oe=605BE302",
      "date_modified": "2021-02-10T20:41:51.000Z",
      "author": {
        "name": "nextdoorkitchenandbar"
      }
    },
    {
      "id": "2505551976048502661",
      "content_html": "<p>Have you made your Valentine’s Day five course dinner reservations yet? Call 518-309-3249\n\n#valentinesday #valentinesday2021 #saratogafoodadventures #ballstonspa #livebspa #eatnextdoor</p><p><img src=\"https://scontent-lga3-2.cdninstagram.com/v/t51.2885-15/e35/p1080x1080/147615638_709764833260738_8597586817728585187_n.jpg?_nc_ht=scontent-lga3-2.cdninstagram.com&_nc_cat=110&_nc_ohc=e2JAGByf6ScAX-bqFIN&tp=1&oh=151059e6bf7cd487d47276a3fb3bdd01&oe=605907DB\" alt=\"\" /></p>",
      "url": "https://instagram.com/p/CLFgj9KpieF",
      "title": "Have you made your Valentine’s Day five course dinner reservations yet? Call 518-309-3249",
      "image": "https://scontent-lga3-2.cdninstagram.com/v/t51.2885-15/e35/p1080x1080/147615638_709764833260738_8597586817728585187_n.jpg?_nc_ht=scontent-lga3-2.cdninstagram.com&_nc_cat=110&_nc_ohc=e2JAGByf6ScAX-bqFIN&tp=1&oh=151059e6bf7cd487d47276a3fb3bdd01&oe=605907DB",
      "date_modified": "2021-02-09T21:11:32.000Z",
      "author": {
        "name": "nextdoorkitchenandbar"
      }
    },
    {
      "id": "2504784040677448988",
      "content_html": "<p>Have you pre-ordered your Valentine’s Day Takeout Package yet? Call 518-309-3249\n\n#valentinesday #valentinesday2021 #518eats #saratogaeats #livebspa #eatnextdoor</p><p><img src=\"https://scontent-lga3-2.cdninstagram.com/v/t51.2885-15/e35/p1080x1080/147129805_4389732867706427_6352334930391857280_n.jpg?_nc_ht=scontent-lga3-2.cdninstagram.com&_nc_cat=111&_nc_ohc=zbrfGDKBz-EAX92RGir&tp=1&oh=9c36d58ce4b553b32397db56e120c321&oe=605C052E\" alt=\"\" /></p>",
      "url": "https://instagram.com/p/CLCx9BnpZ0c",
      "title": "Have you pre-ordered your Valentine’s Day Takeout Package yet? Call 518-309-3249",
      "image": "https://scontent-lga3-2.cdninstagram.com/v/t51.2885-15/e35/p1080x1080/147129805_4389732867706427_6352334930391857280_n.jpg?_nc_ht=scontent-lga3-2.cdninstagram.com&_nc_cat=111&_nc_ohc=zbrfGDKBz-EAX92RGir&tp=1&oh=9c36d58ce4b553b32397db56e120c321&oe=605C052E",
      "date_modified": "2021-02-08T19:45:47.000Z",
      "author": {
        "name": "nextdoorkitchenandbar"
      }
    },
    {
      "id": "2502665119375566674",
      "content_html": "<p>Don’t forget to place your orders for the Super Bowl!  #pizza #wings #salads #familypacks #spreadthebread #superbowleats</p><p><img src=\"https://scontent-lga3-2.cdninstagram.com/v/t51.2885-15/e35/s1080x1080/145994432_502886771073566_1920213119230625495_n.jpg?_nc_ht=scontent-lga3-2.cdninstagram.com&_nc_cat=102&_nc_ohc=0QXYKPtywUAAX_pnvim&tp=1&oh=8cc6b7428d6e56411bacc1cba9c762e3&oe=6059AC38\" alt=\"\" /></p>",
      "url": "https://instagram.com/p/CK7QKqYJCdS",
      "title": "Don’t forget to place your orders for the Super Bowl",
      "image": "https://scontent-lga3-2.cdninstagram.com/v/t51.2885-15/e35/s1080x1080/145994432_502886771073566_1920213119230625495_n.jpg?_nc_ht=scontent-lga3-2.cdninstagram.com&_nc_cat=102&_nc_ohc=0QXYKPtywUAAX_pnvim&tp=1&oh=8cc6b7428d6e56411bacc1cba9c762e3&oe=6059AC38",
      "date_modified": "2021-02-05T21:35:52.000Z",
      "author": {
        "name": "flatbread.social"
      }
    },
    {
      "id": "2501245910724650484",
      "content_html": "<p>Special for the week:  Wood-fired Clams, Shrimp, Mussels in a Spicy Tomato Broth with a couple of slices of our House Focaccia. Sh*t, we’ll wood-fire anything in these bad boys. We’re even working on a wood-fired ice cream special. #harryandlloyd #woodfired #spreadthebread</p><p><img src=\"https://scontent-lga3-2.cdninstagram.com/v/t51.2885-15/e35/s1080x1080/145346227_918687222295955_4862371116566222278_n.jpg?_nc_ht=scontent-lga3-2.cdninstagram.com&_nc_cat=111&_nc_ohc=sSjYs7dcy90AX-ek1_t&tp=1&oh=3791d80d70b7f988569d8a57945e1faa&oe=605C450E\" alt=\"\" /></p>",
      "url": "https://instagram.com/p/CK2NedUpCX0",
      "title": "Special for the week:  Wood-fired Clams, Shrimp, Mussels in a Spicy Tomato Broth with a couple of slices of our House Focaccia",
      "image": "https://scontent-lga3-2.cdninstagram.com/v/t51.2885-15/e35/s1080x1080/145346227_918687222295955_4862371116566222278_n.jpg?_nc_ht=scontent-lga3-2.cdninstagram.com&_nc_cat=111&_nc_ohc=sSjYs7dcy90AX-ek1_t&tp=1&oh=3791d80d70b7f988569d8a57945e1faa&oe=605C450E",
      "date_modified": "2021-02-03T22:36:09.000Z",
      "author": {
        "name": "flatbread.social"
      }
    },
    {
      "id": "2499772106320254768",
      "content_html": "<p>Big Sunday coming up. Treat yourself with our SB Takeout Family meal!  It’s the champion ... of Super Bowl Takeout!  Eh?  Get it? Ok fine. But it IS delicious and WILL make the Super Bowl more fun for you. Call us the shop or order online to reserve yours now!  #superbowl #spreadthebread #treatyoself</p><p><img src=\"https://scontent-lga3-2.cdninstagram.com/v/t51.2885-15/e35/145149846_237140208028880_3873327343660642875_n.jpg?_nc_ht=scontent-lga3-2.cdninstagram.com&_nc_cat=108&_nc_ohc=yW_tGEsLFGYAX-VmHiy&tp=1&oh=bf7ff3402c1f84c9e54ec43b410c60f1&oe=605C5C8B\" alt=\"\" /></p>",
      "url": "https://instagram.com/p/CKw-XyAphcw",
      "title": "Big Sunday coming up",
      "image": "https://scontent-lga3-2.cdninstagram.com/v/t51.2885-15/e35/145149846_237140208028880_3873327343660642875_n.jpg?_nc_ht=scontent-lga3-2.cdninstagram.com&_nc_cat=108&_nc_ohc=yW_tGEsLFGYAX-VmHiy&tp=1&oh=bf7ff3402c1f84c9e54ec43b410c60f1&oe=605C5C8B",
      "date_modified": "2021-02-01T21:47:58.000Z",
      "author": {
        "name": "flatbread.social"
      }
    },
    {
      "id": "2498198950891490189",
      "content_html": "<p>We know. It’s f@%*! cold outside. But it’s nice and warm up in here! Come on down and have a pint.. Or two.. Or more. We don’t judge! #daydrinkingatitsfinest #dwightschruteknows #spreadthebread</p><p><img src=\"https://scontent-lga3-2.cdninstagram.com/v/t51.2885-15/e35/s1080x1080/143836290_852915055281320_3066104345162418880_n.jpg?_nc_ht=scontent-lga3-2.cdninstagram.com&_nc_cat=108&_nc_ohc=ATrRZlX9UtAAX8e6a1w&tp=1&oh=3e22589bf509953f65391d2bc29137be&oe=60591FEC\" alt=\"\" /></p>",
      "url": "https://instagram.com/p/CKrYrW2JAuN",
      "title": "We know",
      "image": "https://scontent-lga3-2.cdninstagram.com/v/t51.2885-15/e35/s1080x1080/143836290_852915055281320_3066104345162418880_n.jpg?_nc_ht=scontent-lga3-2.cdninstagram.com&_nc_cat=108&_nc_ohc=ATrRZlX9UtAAX8e6a1w&tp=1&oh=3e22589bf509953f65391d2bc29137be&oe=60591FEC",
      "date_modified": "2021-01-30T17:42:23.000Z",
      "author": {
        "name": "flatbread.social"
      }
    },
    {
      "id": "2497499007436620056",
      "content_html": "<p>Amazing food specials this weekend AND all night happy hour on Friday for teachers appreciation! Grab yourself a $5 drink and pay it forward by buying one for a teacher! #buyateacheradrink #theyveearnedit #spreadthebread #spreadthelove</p><p><img src=\"https://scontent-lga3-2.cdninstagram.com/v/t51.2885-15/e35/p1080x1080/143310167_423518318890916_7440419281061951791_n.jpg?_nc_ht=scontent-lga3-2.cdninstagram.com&_nc_cat=108&_nc_ohc=wWcN5KupZL8AX_qr3En&tp=1&oh=1964436959784e7fbd5fec71b664c565&oe=605A71BA\" alt=\"\" /></p>",
      "url": "https://instagram.com/p/CKo5h1tJoEY",
      "title": "Amazing food specials this weekend AND all night happy hour on Friday for teachers appreciation",
      "image": "https://scontent-lga3-2.cdninstagram.com/v/t51.2885-15/e35/p1080x1080/143310167_423518318890916_7440419281061951791_n.jpg?_nc_ht=scontent-lga3-2.cdninstagram.com&_nc_cat=108&_nc_ohc=wWcN5KupZL8AX_qr3En&tp=1&oh=1964436959784e7fbd5fec71b664c565&oe=605A71BA",
      "date_modified": "2021-01-29T18:31:44.000Z",
      "author": {
        "name": "flatbread.social"
      }
    },
    {
      "id": "2496806996240859202",
      "content_html": "<p>It’s a blue bird day in Sunny Upstate.  Take advantage and come hang out at the bar or grab some takeout. Either way, get outside. It’s good for you. #spreadthebread #upstate #nobadweatherjustbadclothes</p><p><img src=\"https://scontent-lga3-2.cdninstagram.com/v/t51.2885-15/e35/p1080x1080/142602115_748782002444763_6355762770614388738_n.jpg?_nc_ht=scontent-lga3-2.cdninstagram.com&_nc_cat=103&_nc_ohc=uDhf0E0H9hgAX86_KCu&tp=1&oh=b76e9801d0b0b955110b61ba27eefb56&oe=605A9DC6\" alt=\"\" /></p>",
      "url": "https://instagram.com/p/CKmcLwDpYBC",
      "title": "It’s a blue bird day in Sunny Upstate",
      "image": "https://scontent-lga3-2.cdninstagram.com/v/t51.2885-15/e35/p1080x1080/142602115_748782002444763_6355762770614388738_n.jpg?_nc_ht=scontent-lga3-2.cdninstagram.com&_nc_cat=103&_nc_ohc=uDhf0E0H9hgAX86_KCu&tp=1&oh=b76e9801d0b0b955110b61ba27eefb56&oe=605A9DC6",
      "date_modified": "2021-01-28T19:36:49.000Z",
      "author": {
        "name": "flatbread.social"
      }
    },
    {
      "id": "2492510473722243059",
      "content_html": "<p>Friday, January 29th at Flatbread Social:  All Night Happy Hour AND - Teachers Drink free! $5 Cocktails, $10 Bottles of Wine, $20 Growler Fills.  The deal is opened to everyone, but we’re encouraging everyone to buy a drink for a teacher. They need them. Teachers - call and claim your drinks! #teachersdrinkfree #allnighthappyhour #teachersofinstagram #teacherlife #teachingduringapandemic #spreadthebread</p><p><img src=\"https://scontent-lga3-2.cdninstagram.com/v/t51.2885-15/e35/140584462_2457470437881058_65321494968755367_n.jpg?_nc_ht=scontent-lga3-2.cdninstagram.com&_nc_cat=110&_nc_ohc=jEhCleM4GYoAX_hoQ8V&tp=1&oh=d2e163e9b3c82d0d0fbeceed31d00089&oe=60339650\" alt=\"\" /></p>",
      "url": "https://instagram.com/p/CKXLRHpJ6fz",
      "title": "Friday, January 29th at Flatbread Social:  All Night Happy Hour AND - Teachers Drink free",
      "image": "https://scontent-lga3-2.cdninstagram.com/v/t51.2885-15/e35/140584462_2457470437881058_65321494968755367_n.jpg?_nc_ht=scontent-lga3-2.cdninstagram.com&_nc_cat=110&_nc_ohc=jEhCleM4GYoAX_hoQ8V&tp=1&oh=d2e163e9b3c82d0d0fbeceed31d00089&oe=60339650",
      "date_modified": "2021-01-22T21:28:45.000Z",
      "author": {
        "name": "flatbread.social"
      }
    },
    {
      "id": "2491792508164986640",
      "content_html": "<p>We’re rolling a caprese salad special this week featuring our very own house-made fresh Mozz! Available for dine-in and take-out. #capresesalad #mozzarellaalways #healthyfood</p><p><img src=\"https://scontent-lga3-2.cdninstagram.com/v/t51.2885-15/e35/s1080x1080/140715128_744451266209503_2818114211837728041_n.jpg?_nc_ht=scontent-lga3-2.cdninstagram.com&_nc_cat=107&_nc_ohc=ZdPhxfYmy98AX-jsZ76&tp=1&oh=0f0da6747315ac9365ee2db78c04bab8&oe=605C1A26\" alt=\"\" /></p>",
      "url": "https://instagram.com/p/CKUoBWHJ1cQ",
      "title": "We’re rolling a caprese salad special this week featuring our very own house-made fresh Mozz",
      "image": "https://scontent-lga3-2.cdninstagram.com/v/t51.2885-15/e35/s1080x1080/140715128_744451266209503_2818114211837728041_n.jpg?_nc_ht=scontent-lga3-2.cdninstagram.com&_nc_cat=107&_nc_ohc=ZdPhxfYmy98AX-jsZ76&tp=1&oh=0f0da6747315ac9365ee2db78c04bab8&oe=605C1A26",
      "date_modified": "2021-01-21T21:33:56.000Z",
      "author": {
        "name": "flatbread.social"
      }
    },
    {
      "id": "2487431072986791695",
      "content_html": "<p>We know entertaining your kids is tough these days. SO - we’re including a picture of Flatbread Fred for your kids to color during dinner. We thought about calling him Flatbread Tim, or Flatbread Steve, but the rhyming and alliteration were too much to pass up. Anyway ... we’re here for you. We do it ... for the kids. #flatbreadsocialdistancing #flatbreadfred #forthekids</p><p><img src=\"https://scontent-lga3-2.cdninstagram.com/v/t51.2885-15/e35/139007293_148136606951036_5909039044458290505_n.jpg?_nc_ht=scontent-lga3-2.cdninstagram.com&_nc_cat=108&_nc_ohc=ZoQOxcLUhqwAX9WxhcU&tp=1&oh=fb709be8b8d073b24c223a9fa89efc6a&oe=6033B7FB\" alt=\"\" /></p>",
      "url": "https://instagram.com/p/CKFIWHEpX8P",
      "title": "We know entertaining your kids is tough these days",
      "image": "https://scontent-lga3-2.cdninstagram.com/v/t51.2885-15/e35/139007293_148136606951036_5909039044458290505_n.jpg?_nc_ht=scontent-lga3-2.cdninstagram.com&_nc_cat=108&_nc_ohc=ZoQOxcLUhqwAX9WxhcU&tp=1&oh=fb709be8b8d073b24c223a9fa89efc6a&oe=6033B7FB",
      "date_modified": "2021-01-15T21:08:32.000Z",
      "author": {
        "name": "flatbread.social"
      }
    },
    {
      "id": "2431404674086406779",
      "content_html": "<p>Today I paid off my student loan debt.\n\nCake by @twobirdsmarketplace</p><p><img src=\"https://scontent-lga3-2.cdninstagram.com/v/t51.2885-15/e35/s1080x1080/123245645_1059345254525114_1611454811250817146_n.jpg?_nc_ht=scontent-lga3-2.cdninstagram.com&_nc_cat=102&_nc_ohc=oxSmPyA9_5YAX-CxjsG&tp=1&oh=3606af6867b561b2726ea48d04ab197b&oe=605AA0A6\" alt=\"\" /></p>",
      "url": "https://instagram.com/p/CG-FatAJQp7",
      "title": "Today I paid off my student loan debt",
      "image": "https://scontent-lga3-2.cdninstagram.com/v/t51.2885-15/e35/s1080x1080/123245645_1059345254525114_1611454811250817146_n.jpg?_nc_ht=scontent-lga3-2.cdninstagram.com&_nc_cat=102&_nc_ohc=oxSmPyA9_5YAX-CxjsG&tp=1&oh=3606af6867b561b2726ea48d04ab197b&oe=605AA0A6",
      "date_modified": "2020-10-30T13:54:05.000Z",
      "author": {
        "name": "katydecorah"
      }
    },
    {
      "id": "2173588080672540774",
      "content_html": "<p>Apple sheet cake</p><p><img src=\"https://scontent-lga3-2.cdninstagram.com/v/t51.2885-15/e35/s1080x1080/71886735_532705957528329_6522322102253595207_n.jpg?_nc_ht=scontent-lga3-2.cdninstagram.com&_nc_cat=109&_nc_ohc=E0MkbpfuYI4AX8NtgkN&tp=1&oh=fb9cb333923053d1d315732dc19913de&oe=605B15AC\" alt=\"\" /></p>",
      "url": "https://instagram.com/p/B4qItfcgohm",
      "title": "Apple sheet cake",
      "image": "https://scontent-lga3-2.cdninstagram.com/v/t51.2885-15/e35/s1080x1080/71886735_532705957528329_6522322102253595207_n.jpg?_nc_ht=scontent-lga3-2.cdninstagram.com&_nc_cat=109&_nc_ohc=E0MkbpfuYI4AX8NtgkN&tp=1&oh=fb9cb333923053d1d315732dc19913de&oe=605B15AC",
      "date_modified": "2019-11-09T20:38:32.000Z",
      "author": {
        "name": "katydecorah"
      }
    },
    {
      "id": "2166889962656668071",
      "content_html": "<p>We are monster foodies!</p><p><img src=\"https://scontent-lga3-2.cdninstagram.com/v/t51.2885-15/e35/s1080x1080/72291222_178059880030486_627605298652157995_n.jpg?_nc_ht=scontent-lga3-2.cdninstagram.com&_nc_cat=110&_nc_ohc=id6q5JP3jIIAX86a8PZ&tp=1&oh=391605f65cb77bbf95b48c3931631e8f&oe=605B72DE\" alt=\"\" /></p>",
      "url": "https://instagram.com/p/B4SVvC7gpmn",
      "title": "We are monster foodies",
      "image": "https://scontent-lga3-2.cdninstagram.com/v/t51.2885-15/e35/s1080x1080/72291222_178059880030486_627605298652157995_n.jpg?_nc_ht=scontent-lga3-2.cdninstagram.com&_nc_cat=110&_nc_ohc=id6q5JP3jIIAX86a8PZ&tp=1&oh=391605f65cb77bbf95b48c3931631e8f&oe=605B72DE",
      "date_modified": "2019-10-31T14:50:34.000Z",
      "author": {
        "name": "katydecorah"
      }
    },
    {
      "id": "2162720822165245808",
      "content_html": "<p>☾ bitchin</p><p><img src=\"https://scontent-lga3-2.cdninstagram.com/v/t51.2885-15/e35/s1080x1080/72786297_2365693070426381_5929100958132233099_n.jpg?_nc_ht=scontent-lga3-2.cdninstagram.com&_nc_cat=105&_nc_ohc=O1ClU-QyTlgAX8SON4c&tp=1&oh=1b1dae76e57c7b9f80fa9a14c0a59bb0&oe=6059B729\" alt=\"\" /></p>",
      "url": "https://instagram.com/p/B4DhyERgA9w",
      "title": "☾ bitchin",
      "image": "https://scontent-lga3-2.cdninstagram.com/v/t51.2885-15/e35/s1080x1080/72786297_2365693070426381_5929100958132233099_n.jpg?_nc_ht=scontent-lga3-2.cdninstagram.com&_nc_cat=105&_nc_ohc=O1ClU-QyTlgAX8SON4c&tp=1&oh=1b1dae76e57c7b9f80fa9a14c0a59bb0&oe=6059B729",
      "date_modified": "2019-10-25T20:47:14.000Z",
      "author": {
        "name": "katydecorah"
      }
    },
    {
      "id": "2154720547676741908",
      "content_html": "<p>Choux donuts</p><p><img src=\"https://scontent-lga3-2.cdninstagram.com/v/t51.2885-15/e35/s1080x1080/71190752_441886183108477_7988142840093531655_n.jpg?_nc_ht=scontent-lga3-2.cdninstagram.com&_nc_cat=101&_nc_ohc=jNRgxmLctxEAX9PnsXr&tp=1&oh=8ff545c25ba16a074670595b55f6f0ea&oe=605A3C4F\" alt=\"\" /></p>",
      "url": "https://instagram.com/p/B3nGuwCgeEU",
      "title": "Choux donuts",
      "image": "https://scontent-lga3-2.cdninstagram.com/v/t51.2885-15/e35/s1080x1080/71190752_441886183108477_7988142840093531655_n.jpg?_nc_ht=scontent-lga3-2.cdninstagram.com&_nc_cat=101&_nc_ohc=jNRgxmLctxEAX9PnsXr&tp=1&oh=8ff545c25ba16a074670595b55f6f0ea&oe=605A3C4F",
      "date_modified": "2019-10-14T19:52:07.000Z",
      "author": {
        "name": "katydecorah"
      }
    },
    {
      "id": "2149431320818773784",
      "content_html": "<p>Rose apple tart. Recipe by @yossyarefi.</p><p><img src=\"https://scontent-lga3-2.cdninstagram.com/v/t51.2885-15/e35/s1080x1080/72895211_778207925931601_2112736808330979178_n.jpg?_nc_ht=scontent-lga3-2.cdninstagram.com&_nc_cat=101&_nc_ohc=-1kX6JB8XbIAX92I03L&tp=1&oh=4106ce9932c902d0801654036d164f36&oe=6059C5F3\" alt=\"\" /></p>",
      "url": "https://instagram.com/p/B3UUGXqgG8Y",
      "title": "Rose apple tart",
      "image": "https://scontent-lga3-2.cdninstagram.com/v/t51.2885-15/e35/s1080x1080/72895211_778207925931601_2112736808330979178_n.jpg?_nc_ht=scontent-lga3-2.cdninstagram.com&_nc_cat=101&_nc_ohc=-1kX6JB8XbIAX92I03L&tp=1&oh=4106ce9932c902d0801654036d164f36&oe=6059C5F3",
      "date_modified": "2019-10-07T12:43:22.000Z",
      "author": {
        "name": "katydecorah"
      }
    },
    {
      "id": "2133862968882684736",
      "content_html": "undefined<p><img src=\"https://scontent-lga3-2.cdninstagram.com/v/t51.2885-15/e35/s1080x1080/70737581_105544737401545_1399334489263432147_n.jpg?_nc_ht=scontent-lga3-2.cdninstagram.com&_nc_cat=101&_nc_ohc=ftxnNQMEcXQAX-9U8Jo&tp=1&oh=71b53612610609aa42235ce4423dccc9&oe=605B8939\" alt=\"\" /></p>",
      "url": "https://instagram.com/p/B2dARCDnONA",
      "image": "https://scontent-lga3-2.cdninstagram.com/v/t51.2885-15/e35/s1080x1080/70737581_105544737401545_1399334489263432147_n.jpg?_nc_ht=scontent-lga3-2.cdninstagram.com&_nc_cat=101&_nc_ohc=ftxnNQMEcXQAX-9U8Jo&tp=1&oh=71b53612610609aa42235ce4423dccc9&oe=605B8939",
      "date_modified": "2019-09-16T01:11:50.000Z",
      "author": {
        "name": "katydecorah"
      }
    },
    {
      "id": "2128382238700733651",
      "content_html": "undefined<p><img src=\"https://scontent-lga3-2.cdninstagram.com/v/t51.2885-15/e35/s1080x1080/67841550_724311197981702_6136181798484813957_n.jpg?_nc_ht=scontent-lga3-2.cdninstagram.com&_nc_cat=102&_nc_ohc=SpmJhwsZ2CgAX__DT9j&tp=1&oh=1e7264b5781200c34fe7d170193a6db7&oe=605A3365\" alt=\"\" /></p>",
      "url": "https://instagram.com/p/B2JiF6UAgTT",
      "image": "https://scontent-lga3-2.cdninstagram.com/v/t51.2885-15/e35/s1080x1080/67841550_724311197981702_6136181798484813957_n.jpg?_nc_ht=scontent-lga3-2.cdninstagram.com&_nc_cat=102&_nc_ohc=SpmJhwsZ2CgAX__DT9j&tp=1&oh=1e7264b5781200c34fe7d170193a6db7&oe=605A3365",
      "date_modified": "2019-09-08T11:42:36.000Z",
      "author": {
        "name": "katydecorah"
      }
    },
    {
      "id": "2127907940858670468",
      "content_html": "undefined<p><img src=\"https://scontent-lga3-2.cdninstagram.com/v/t51.2885-15/e35/p1080x1080/67681756_2715739055158177_1478089007444277229_n.jpg?_nc_ht=scontent-lga3-2.cdninstagram.com&_nc_cat=101&_nc_ohc=wg-A_Av2EzUAX_Yinty&tp=1&oh=8aafcb2881168bfde983bd0a0f23c356&oe=605A0B66\" alt=\"\" /></p>",
      "url": "https://instagram.com/p/B2H2P-BnS2E",
      "image": "https://scontent-lga3-2.cdninstagram.com/v/t51.2885-15/e35/p1080x1080/67681756_2715739055158177_1478089007444277229_n.jpg?_nc_ht=scontent-lga3-2.cdninstagram.com&_nc_cat=101&_nc_ohc=wg-A_Av2EzUAX_Yinty&tp=1&oh=8aafcb2881168bfde983bd0a0f23c356&oe=605A0B66",
      "date_modified": "2019-09-07T20:00:15.000Z",
      "author": {
        "name": "katydecorah"
      }
    },
    {
      "id": "2122738241866893757",
      "content_html": "<p>Jason and I are in a Times Union article today about working from home. (Photos by Will Waldron)</p><p><img src=\"https://scontent-lga3-2.cdninstagram.com/v/t51.2885-15/e35/s1080x1080/69425380_146041686601701_4846739388620734892_n.jpg?_nc_ht=scontent-lga3-2.cdninstagram.com&_nc_cat=109&_nc_ohc=uh9R92ZV-8MAX_yxPHc&tp=1&oh=00ee9e8e1ba6985438a5ace068341440&oe=605AA5DF\" alt=\"\" /></p>",
      "url": "https://instagram.com/p/B11ey8pnQm9",
      "title": "Jason and I are in a Times Union article today about working from home",
      "image": "https://scontent-lga3-2.cdninstagram.com/v/t51.2885-15/e35/s1080x1080/69425380_146041686601701_4846739388620734892_n.jpg?_nc_ht=scontent-lga3-2.cdninstagram.com&_nc_cat=109&_nc_ohc=uh9R92ZV-8MAX_yxPHc&tp=1&oh=00ee9e8e1ba6985438a5ace068341440&oe=605AA5DF",
      "date_modified": "2019-08-31T16:48:59.000Z",
      "author": {
        "name": "katydecorah"
      }
    },
    {
      "id": "2117704113792970888",
      "content_html": "<p>Cowboy cookie ice cream. (My first try at writing a dairy-free recipe and my first time making granola. Due to my reflection in the scoop, this is also a selfie.)</p><p><img src=\"https://scontent-lga3-2.cdninstagram.com/v/t51.2885-15/e35/s1080x1080/67178229_1274041706103256_5381338537786988100_n.jpg?_nc_ht=scontent-lga3-2.cdninstagram.com&_nc_cat=104&_nc_ohc=Pz0NePOA5boAX_rjFuM&tp=1&oh=e2fd356bef386767eaa95304b3587dd4&oe=605AAE8D\" alt=\"\" /></p>",
      "url": "https://instagram.com/p/B1jmKviA3CI",
      "title": "Cowboy cookie ice cream",
      "image": "https://scontent-lga3-2.cdninstagram.com/v/t51.2885-15/e35/s1080x1080/67178229_1274041706103256_5381338537786988100_n.jpg?_nc_ht=scontent-lga3-2.cdninstagram.com&_nc_cat=104&_nc_ohc=Pz0NePOA5boAX_rjFuM&tp=1&oh=e2fd356bef386767eaa95304b3587dd4&oe=605AAE8D",
      "date_modified": "2019-08-24T18:07:04.000Z",
      "author": {
        "name": "katydecorah"
      }
    },
    {
      "id": "2117122775289202996",
      "content_html": "<p>🌱</p><p><img src=\"https://scontent-lga3-2.cdninstagram.com/v/t51.2885-15/e35/s1080x1080/67514469_105482600715402_358065942120119909_n.jpg?_nc_ht=scontent-lga3-2.cdninstagram.com&_nc_cat=106&_nc_ohc=167sU8iYWb0AX_Jr1r5&tp=1&oh=39f9986052fdd8841f2a82fcf303af5f&oe=605BEA07\" alt=\"\" /></p>",
      "url": "https://instagram.com/p/B1hh_J3AIk0",
      "title": "🌱",
      "image": "https://scontent-lga3-2.cdninstagram.com/v/t51.2885-15/e35/s1080x1080/67514469_105482600715402_358065942120119909_n.jpg?_nc_ht=scontent-lga3-2.cdninstagram.com&_nc_cat=106&_nc_ohc=167sU8iYWb0AX_Jr1r5&tp=1&oh=39f9986052fdd8841f2a82fcf303af5f&oe=605BEA07",
      "date_modified": "2019-08-23T22:52:03.000Z",
      "author": {
        "name": "katydecorah"
      }
    }
  ]
}
